sydraw/__init__.py
sydraw/__main__.py
sydraw/cli.py
sydraw/gui.py
sydraw/linalg.py
sydraw/synth.py
sydraw/utils/__init__.py
sydraw/utils/cameraops.py
sydraw/utils/config.py
sydraw/utils/utils.py
sydraw-0.0.3.dist-info/LICENSE.md
sydraw-0.0.3.dist-info/METADATA
sydraw-0.0.3.dist-info/WHEEL
sydraw-0.0.3.dist-info/entry_points.txt
sydraw-0.0.3.dist-info/RECORD
