Metadata-Version: 2.1
Name: sydraw
Version: 0.0.3
Summary: A python library that helps you create synthetic 2D point clouds dataset
Home-page: https://pypi.org/project/sydraw
License: MIT
Author: William Bonvini
Author-email: william.bonvini@outlook.com
Requires-Python: >=3.9.5,<3.12
Classifier: Development Status :: 2 - Pre-Alpha
Classifier: License :: OSI Approved :: MIT License
Classifier: Natural Language :: English
Classifier: Operating System :: OS Independent
Classifier: Programming Language :: Python
Classifier: Programming Language :: Python :: 3
Classifier: Programming Language :: Python :: 3.10
Classifier: Programming Language :: Python :: 3.11
Classifier: Programming Language :: Python :: 3
Classifier: Programming Language :: Python :: 3.9
Requires-Dist: matplotlib (>=3.7)
Requires-Dist: numpy
Requires-Dist: scipy
Project-URL: Documentation, https://sydraw.readthedocs.io
Project-URL: Repository, https://github.com/WilliamBonvini/sydraw
